[
  {
    "title": "Health-Metrics",
    "imageSrc": "projects/Health.PNG",
    "description": "HealthMetrics is a modern, user-friendly web application.",
    "skills": ["HTML5", "CSS3", "JavaScript"],
    "demo": "https://keshala123.github.io/Health-Metrics/",
    "source": "https://github.com/Keshala123/Health-Metrics"
  },
  {
    "title": "Library Management System",
    "imageSrc": "projects/library.jpg",
    "description": "This is a simple Library Management System built using Java",
    "skills": ["Java"],
    "demo": "https://keshala123.github.io/Library-Management-system/",
    "source": "https://github.com/Keshala123/Library-Management-system"
  },
  {
    "title": "Academic To-Do-List",
    "imageSrc": "projects/todolist.PNG",
    "description": "It helps students manage tasks across different work categories",
    "skills": ["HTML5", "CSS3", "JavaScript"],
    "demo": "https://keshala123.github.io/To-Do-List/",
    "source": "https://github.com/Keshala123/To-Do-List"
  }
]
